entropy/__init__.py
entropy/config.py
entropy/cli/__init__.py
entropy/cli/app.py
entropy/cli/display.py
entropy/cli/utils.py
entropy/cli/commands/__init__.py
entropy/cli/commands/config_cmd.py
entropy/cli/commands/extend.py
entropy/cli/commands/network.py
entropy/cli/commands/persona.py
entropy/cli/commands/results.py
entropy/cli/commands/sample.py
entropy/cli/commands/scenario.py
entropy/cli/commands/simulate.py
entropy/cli/commands/spec.py
entropy/cli/commands/validate.py
entropy/core/__init__.py
entropy/core/llm.py
entropy/core/rate_limiter.py
entropy/core/rate_limits.py
entropy/core/models/__init__.py
entropy/core/models/network.py
entropy/core/models/population.py
entropy/core/models/results.py
entropy/core/models/sampling.py
entropy/core/models/scenario.py
entropy/core/models/simulation.py
entropy/core/models/validation.py
entropy/core/providers/__init__.py
entropy/core/providers/base.py
entropy/core/providers/claude.py
entropy/core/providers/logging.py
entropy/core/providers/openai.py
entropy/population/__init__.py
entropy/population/network/__init__.py
entropy/population/network/config.py
entropy/population/network/generator.py
entropy/population/network/metrics.py
entropy/population/network/similarity.py
entropy/population/persona/__init__.py
entropy/population/persona/config.py
entropy/population/persona/generator.py
entropy/population/persona/renderer.py
entropy/population/persona/stats.py
entropy/population/sampler/__init__.py
entropy/population/sampler/core.py
entropy/population/sampler/distributions.py
entropy/population/sampler/modifiers.py
entropy/population/spec_builder/__init__.py
entropy/population/spec_builder/binder.py
entropy/population/spec_builder/hydrator.py
entropy/population/spec_builder/parsers.py
entropy/population/spec_builder/schemas.py
entropy/population/spec_builder/selector.py
entropy/population/spec_builder/sufficiency.py
entropy/population/spec_builder/hydrators/__init__.py
entropy/population/spec_builder/hydrators/conditional.py
entropy_predict-0.1.0.dist-info/METADATA
entropy_predict-0.1.0.dist-info/WHEEL
entropy_predict-0.1.0.dist-info/entry_points.txt
entropy_predict-0.1.0.dist-info/licenses/LICENSE
entropy_predict-0.1.0.dist-info/RECORD
