Metadata-Version: 2.4
Name: entropy-predict
Version: 0.1.0
Summary: Predictive intelligence through agent-based population simulation
Project-URL: Homepage, https://github.com/exaforge/entropy
Project-URL: Repository, https://github.com/exaforge/entropy
Project-URL: Issues, https://github.com/exaforge/entropy/issues
Author: Devesh Paragiri
License-Expression: MIT
License-File: LICENSE
Keywords: agent-based,llm,population,predictive-intelligence,simulation
Classifier: Development Status :: 3 - Alpha
Classifier: Intended Audience :: Developers
Classifier: Intended Audience :: Science/Research
Classifier: License :: OSI Approved :: MIT License
Classifier: Programming Language :: Python :: 3
Classifier: Programming Language :: Python :: 3.11
Classifier: Programming Language :: Python :: 3.12
Classifier: Programming Language :: Python :: 3.13
Classifier: Topic :: Scientific/Engineering :: Artificial Intelligence
Requires-Python: >=3.11
Requires-Dist: anthropic>=0.77.0
Requires-Dist: fastapi>=0.115.0
Requires-Dist: networkx>=3.4.0
Requires-Dist: numpy>=2.0.0
Requires-Dist: openai>=1.50.0
Requires-Dist: pydantic>=2.9.0
Requires-Dist: python-dotenv>=1.0.0
Requires-Dist: pyyaml>=6.0.0
Requires-Dist: rich>=13.0.0
Requires-Dist: scipy>=1.14.0
Requires-Dist: typer>=0.12.0
Requires-Dist: uvicorn>=0.32.0
Provides-Extra: dev
Requires-Dist: pytest-asyncio>=0.24.0; extra == 'dev'
Requires-Dist: pytest>=8.0.0; extra == 'dev'
Requires-Dist: ruff>=0.14.0; extra == 'dev'
